thants/__init__.py
thants/actions.py
thants/envs/__init__.py
thants/envs/mono.py
thants/envs/multi.py
thants/envs/presets.py
thants/generators/__init__.py
thants/generators/colonies/__init__.py
thants/generators/colonies/mono.py
thants/generators/colonies/multi.py
thants/generators/colonies/utils.py
thants/generators/food.py
thants/generators/terrain.py
thants/observations.py
thants/py.typed
thants/rewards.py
thants/signals.py
thants/specs.py
thants/steps.py
thants/types.py
thants/viewer.py
thants-0.3.4.dist-info/LICENSE.txt
thants-0.3.4.dist-info/METADATA
thants-0.3.4.dist-info/WHEEL
thants-0.3.4.dist-info/RECORD
